{
  "items": [
    {
      "date": "2026-07-19 22:12",
      "type": "mentor",
      "icon": "📚",
      "text": "국어, 수학, 생활윤리 멘토링 완료",
      "sub": ""
    },
    {
      "date": "2026-07-19 13:44",
      "type": "apply",
      "icon": "📌",
      "text": "관리형독서실 대기 신청 접수",
      "sub": ""
    },
    {
      "date": "2026-07-19 09:39",
      "type": "mentor",
      "icon": "📚",
      "text": "세계지리, 사문, 국어(화작·문학·독서), 수학 멘토링 완료",
      "sub": ""
    },
    {
      "date": "2026-07-19 09:34",
      "type": "mentor",
      "icon": "📚",
      "text": "국어, 영어, 사탐(사문, 생윤) 멘토링 완료",
      "sub": ""
    },
    {
      "date": "2026-07-19 09:31",
      "type": "mentor",
      "icon": "📚",
      "text": "국어 (문학, 독서) 멘토링 완료",
      "sub": ""
    },
    {
      "date": "2026-07-19 09:29",
      "type": "mentor",
      "icon": "📚",
      "text": "국어, 수학, 영어, 사회탐구(생윤, 사문) 멘토링 완료",
      "sub": ""
    },
    {
      "date": "2026-07-19 09:21",
      "type": "mentor",
      "icon": "📚",
      "text": "국어(화작, 독서, 문학), 수학(확통), 영어, 생활과 윤리, 사회문화 멘토링 완료",
      "sub": ""
    },
    {
      "date": "2026-07-19 09:19",
      "type": "mentor",
      "icon": "📚",
      "text": "국어, 수학, 사탐(세계지리, 사문), 한국사, 수리논술 멘토링 완료",
      "sub": ""
    },
    {
      "date": "2026-07-19 09:15",
      "type": "mentor",
      "icon": "📚",
      "text": "국어(화작·문학·독서), 영어, 탐구(생윤·사문), 수학 멘토링 완료",
      "sub": ""
    },
    {
      "date": "2026-07-19 09:10",
      "type": "mentor",
      "icon": "📚",
      "text": "수학, 국어, 영어, 사회문화, 생활과윤리 멘토링 완료",
      "sub": ""
    }
  ],
  "lastUpdated": "2026-07-19 22:12"
}